{
  "version": 1,
  "projects": [
    {
      "referenceFileName": "BetterEducationInfoview",
      "path": "project/en-US/Mod/BetterEducationInfoview.json",
      "name": "Better Education Infoview",
      "link": "https://mods.paradoxplaza.com/mods/149918/Windows",
      "aka": [
        "BetterEducationInfoView.LocaleEN"
      ],
      "frozen": true,
      "updatedAt": "2026-07-04T09:57:27.216Z",
      "updatedBy": {
        "id": 36119339,
        "login": "baka-gourd",
        "name": "baka-gourd",
        "avatarUrl": "https://avatars.githubusercontent.com/u/36119339?v=4"
      }
    },
    {
      "referenceFileName": "BetterTransitView",
      "path": "project/en-US/Mod/BetterTransitView.json",
      "name": "Better Transit View",
      "link": "https://mods.paradoxplaza.com/mods/139595/Windows",
      "aka": [
        "BetterTransitView.ModSettings.LocaleEN"
      ],
      "frozen": true,
      "updatedAt": "2026-06-10T12:05:10.873Z",
      "updatedBy": {
        "id": 36119339,
        "login": "baka-gourd",
        "name": "baka-gourd",
        "avatarUrl": "https://avatars.githubusercontent.com/u/36119339?v=4"
      }
    },
    {
      "referenceFileName": "RealisticParking",
      "link": "https://mods.paradoxplaza.com/mods/87313/Windows",
      "name": "Realistic Parking",
      "aka": [
        "RealisticParking.LocaleEN"
      ],
      "frozen": false,
      "path": "project/en-US/Mod/RealisticParking.json",
      "updatedAt": "2026-07-04T10:13:41.118Z",
      "updatedBy": {
        "id": 36119339,
        "login": "baka-gourd",
        "name": "baka-gourd",
        "avatarUrl": "https://avatars.githubusercontent.com/u/36119339?v=4"
      }
    },
    {
      "referenceFileName": "RealisticPathFinding",
      "path": "project/en-US/Mod/RealisticPathFinding.json",
      "name": "Realistic PathFinding",
      "link": "https://mods.paradoxplaza.com/mods/121226/Windows",
      "aka": [
        "RealisticPathFinding.LocaleEN"
      ],
      "frozen": true,
      "updatedAt": "2026-06-10T06:38:59.987Z",
      "updatedBy": {
        "id": 36119339,
        "login": "baka-gourd",
        "name": "baka-gourd",
        "avatarUrl": "https://avatars.githubusercontent.com/u/36119339?v=4"
      }
    },
    {
      "referenceFileName": "RealisticWorkplacesAndHouseholds",
      "path": "project/en-US/Mod/RealisticWorkplacesAndHouseholds.json",
      "name": "Realistic Workplaces And Households",
      "link": "https://mods.paradoxplaza.com/mods/87755/Windows",
      "aka": [
        "RealisticWorkplacesAndHouseholds.LocaleEN"
      ],
      "frozen": true,
      "updatedAt": "2026-06-10T12:05:20.325Z",
      "updatedBy": {
        "id": 36119339,
        "login": "baka-gourd",
        "name": "baka-gourd",
        "avatarUrl": "https://avatars.githubusercontent.com/u/36119339?v=4"
      }
    },
    {
      "referenceFileName": "Time2Work",
      "path": "project/en-US/Mod/Time2Work.json",
      "name": "Realistic Trips",
      "link": "https://mods.paradoxplaza.com/mods/77171/Windows",
      "aka": [
        "Time2Work.Setting-LocaleEN"
      ],
      "frozen": true,
      "updatedAt": "2026-07-04T09:46:51.318Z",
      "updatedBy": {
        "id": 36119339,
        "login": "baka-gourd",
        "name": "baka-gourd",
        "avatarUrl": "https://avatars.githubusercontent.com/u/36119339?v=4"
      }
    },
    {
      "referenceFileName": "UrbanInequality",
      "path": "project/en-US/Mod/UrbanInequality.json",
      "name": "UrbanInequality",
      "link": "https://mods.paradoxplaza.com/mods/110245/Windows",
      "aka": [
        "UrbanInequality.Setting-LocaleEN"
      ],
      "frozen": true,
      "updatedAt": "2026-07-04T09:57:34.542Z",
      "updatedBy": {
        "id": 36119339,
        "login": "baka-gourd",
        "name": "baka-gourd",
        "avatarUrl": "https://avatars.githubusercontent.com/u/36119339?v=4"
      }
    }
  ]
}
