{
"Options.SECTION[Time2Work.Time2Work.Mod]": "Realistic Trips",
"Options.TAB[Time2Work.Time2Work.Mod.Settings]": "Настройки",
"Options.TAB[Time2Work.Time2Work.Mod.Work]": "Работа",
"Options.TAB[Time2Work.Time2Work.Mod.Shopping and Leisure]": "Покупки и досуг",
"Options.TAB[Time2Work.Time2Work.Mod.School]": "Школа",
"Options.TAB[Time2Work.Time2Work.Mod.Week]": "Неделя",
"Options.TAB[Time2Work.Time2Work.Mod.Special Events]": "Особые события",
"Options.TAB[Time2Work.Time2Work.Mod.Other]": "Другое",
"Options.GROUP[Time2Work.Time2Work.Mod.MinEventGroup]": "Мин. количество событий в день недели",
"Options.GROUP[Time2Work.Time2Work.Mod.MaxEventGroup]": "Макс. количество событий в день недели",
"Options.GROUP[Time2Work.Time2Work.Mod.WorkPlaceShiftGroup]": "Изменить долю вечерних и ночных смен",
"Options.GROUP[Time2Work.Time2Work.Mod.NonDayShiftByWorkTypeGroup]": "Изменить долю недневных смен по типу работы",
"Options.GROUP[Time2Work.Time2Work.Mod.RemoteGroup]": "Настройки удаленной работы",
"Options.GROUP[Time2Work.Time2Work.Mod.TimeOffGroup]": "Настройки отпусков и праздников",
"Options.GROUP[Time2Work.Time2Work.Mod.DayShiftGroup]": "Настройки дневной смены",
"Options.GROUP[Time2Work.Time2Work.Mod.LeisureMealsGroup]": "Приемы пищи: среднее время досуга в день",
"Options.GROUP[Time2Work.Time2Work.Mod.LeisureEntertainmentGroup]": "Развлечения: среднее время досуга в день",
"Options.GROUP[Time2Work.Time2Work.Mod.LeisureShoppingGroup]": "Покупки: среднее время досуга в день",
"Options.GROUP[Time2Work.Time2Work.Mod.LeisureParksGroup]": "Парки: среднее время досуга в день",
"Options.GROUP[Time2Work.Time2Work.Mod.LeisureTravelGroup]": "Путешествия: среднее время досуга в день",
"Options.GROUP[Time2Work.Time2Work.Mod.ShoppingTimeGroup]": "Среднее время покупок (минуты) для каждого ресурса",
"Options.GROUP[Time2Work.Time2Work.Mod.SchoolTimeOffGroup]": "Настройки школьных каникул",
"Options.GROUP[Time2Work.Time2Work.Mod.SchoolTimeGroup]": "Настройки начала/окончания занятий",
"Options.GROUP[Time2Work.Time2Work.Mod.School1WeekGroup]": "Посещаемость начальной школы по дням",
"Options.GROUP[Time2Work.Time2Work.Mod.School2WeekGroup]": "Посещаемость средней школы по дням",
"Options.GROUP[Time2Work.Time2Work.Mod.School34WeekGroup]": "Посещаемость колледжей и университетов по дням",
"Options.GROUP[Time2Work.Time2Work.Mod.SlowerTimeGroup]": "Настройки дня и времени",
"Options.GROUP[Time2Work.Time2Work.Mod.DTSimulationGroup]": "Симуляция типа дня",
"Options.GROUP[Time2Work.Time2Work.Mod.TrucksGroup]": "Грузовики",
"Options.GROUP[Time2Work.Time2Work.Mod.OtherGroup]": "Другое",
"Options.GROUP[Time2Work.Time2Work.Mod.ExternalGroup]": "Внешние поездки",
"Options.GROUP[Time2Work.Time2Work.Mod.ExpensesGroup]": "Расходы на услуги",
"Options.GROUP[Time2Work.Time2Work.Mod.WeekGroup]": "Процент работников по дням",
"Options.GROUP[Time2Work.Time2Work.Mod.OfficeGroup]": "Офис - процент работников по дням",
"Options.GROUP[Time2Work.Time2Work.Mod.CommercialGroup]": "Коммерция - процент работников по дням",
"Options.GROUP[Time2Work.Time2Work.Mod.IndustryGroup]": "Промышленность - процент работников по дням",
"Options.GROUP[Time2Work.Time2Work.Mod.CityServicesGroup]": "Городские службы - процент работников по дням",
"Options.GROUP[Time2Work.Time2Work.Mod.VisitTimeGroup]": "Время, проведенное в посещении определенных зданий",
"Options.GROUP[Time2Work.Time2Work.Mod.HolidayGroup]": "Праздники",
"Options.OPTION[Time2Work.Time2Work.Mod.Setting.DTText]": "Изменение параметров ниже требует перезапуска игры.",
"Options.OPTION[Time2Work.Time2Work.Mod.Setting.MultilineText]": "ВНИМАНИЕ: Изменение коэффициента замедленного времени для существующих городов изменит возраст жителей, что может вызвать проблемы в игре. Если коэффициент изменен, распределение возрастов населения со временем выровняется.",
"Options.OPTION[Time2Work.Time2Work.Mod.Setting.settings_choice]": "Настройки мода",
"Options.OPTION_DESCRIPTION[Time2Work.Time2Work.Mod.Setting.settings_choice]": "Изменение всех настроек мода. Производительность: обновит настройки для улучшения производительности, похоже на стандартную игру. Сбалансированно: включены большинство функций мода, но несколько с высоким влиянием на производительность отключены. Настройки по странам: данные реального мира собраны для нескольких стран, выбор одной из них сделает игру более реалистичной, но может повлиять на производительность.",
"Options.OPTION[Time2Work.Time2Work.Mod.Setting.Button]": "Подтвердить",
"Options.OPTION_DESCRIPTION[Time2Work.Time2Work.Mod.Setting.Button]": "Подтвердить новые настройки",
"Options.OPTION[Time2Work.Time2Work.Mod.Setting.new_years_num_events]": "Количество событий на Новый год",
"Options.OPTION_DESCRIPTION[Time2Work.Time2Work.Mod.Setting.new_years_num_events]": "Количество событий, которые произойдут в последний день года. Все они заканчиваются в полночь.",
"Options.OPTION[Time2Work.Time2Work.Mod.Setting.meals_weekday]": "Понедельник–четверг",
"Options.OPTION_DESCRIPTION[Time2Work.Time2Work.Mod.Setting.meals_weekday]": "Среднее количество часов, которое человек тратит на походы поесть в день.",
"Options.OPTION[Time2Work.Time2Work.Mod.Setting.meals_avgday]": "Пятница",
"Options.OPTION_DESCRIPTION[Time2Work.Time2Work.Mod.Setting.meals_avgday]": "Среднее количество часов, которое человек тратит на походы поесть в день.",
"Options.OPTION[Time2Work.Time2Work.Mod.Setting.meals_saturday]": "Суббота",
"Options.OPTION_DESCRIPTION[Time2Work.Time2Work.Mod.Setting.meals_saturday]": "Среднее количество часов, которое человек тратит на походы поесть в день.",
"Options.OPTION[Time2Work.Time2Work.Mod.Setting.meals_sunday]": "Воскресенье",
"Options.OPTION_DESCRIPTION[Time2Work.Time2Work.Mod.Setting.meals_sunday]": "Среднее количество часов, которое человек тратит на походы поесть в день.",
"Options.OPTION[Time2Work.Time2Work.Mod.Setting.entertainment_weekday]": "Понедельник–четверг",
"Options.OPTION_DESCRIPTION[Time2Work.Time2Work.Mod.Setting.entertainment_weekday]": "Среднее количество часов, которое человек тратит на развлечения в день.",
"Options.OPTION[Time2Work.Time2Work.Mod.Setting.entertainment_avgday]": "Пятница",
"Options.OPTION_DESCRIPTION[Time2Work.Time2Work.Mod.Setting.entertainment_avgday]": "Среднее количество часов, которое человек тратит на развлечения в день.",
"Options.OPTION[Time2Work.Time2Work.Mod.Setting.entertainment_saturday]": "Суббота",
"Options.OPTION_DESCRIPTION[Time2Work.Time2Work.Mod.Setting.entertainment_saturday]": "Среднее количество часов, которое человек тратит на развлечения в день.",
"Options.OPTION[Time2Work.Time2Work.Mod.Setting.entertainment_sunday]": "Воскресенье",
"Options.OPTION_DESCRIPTION[Time2Work.Time2Work.Mod.Setting.entertainment_sunday]": "Среднее количество часов, которое человек тратит на развлечения в день.",
"Options.OPTION[Time2Work.Time2Work.Mod.Setting.shopping_weekday]": "Понедельник–четверг",
"Options.OPTION_DESCRIPTION[Time2Work.Time2Work.Mod.Setting.shopping_weekday]": "Среднее количество часов, которое человек тратит на походы за покупками в день.",
"Options.OPTION[Time2Work.Time2Work.Mod.Setting.shopping_avgday]": "Пятница",
"Options.OPTION_DESCRIPTION[Time2Work.Time2Work.Mod.Setting.shopping_avgday]": "Среднее количество часов, которое человек тратит на походы за покупками в день.",
"Options.OPTION[Time2Work.Time2Work.Mod.Setting.shopping_saturday]": "Суббота",
"Options.OPTION_DESCRIPTION[Time2Work.Time2Work.Mod.Setting.shopping_saturday]": "Среднее количество часов, которое человек тратит на походы за покупками в день.",
"Options.OPTION[Time2Work.Time2Work.Mod.Setting.shopping_sunday]": "Воскресенье",
"Options.OPTION_DESCRIPTION[Time2Work.Time2Work.Mod.Setting.shopping_sunday]": "Среднее количество часов, которое человек тратит на походы за покупками в день.",
"Options.OPTION[Time2Work.Time2Work.Mod.Setting.park_weekday]": "Понедельник–четверг",
"Options.OPTION_DESCRIPTION[Time2Work.Time2Work.Mod.Setting.park_weekday]": "Среднее количество часов, которое человек тратит на посещение парков в день.",
"Options.OPTION[Time2Work.Time2Work.Mod.Setting.park_avgday]": "Пятница",
"Options.OPTION_DESCRIPTION[Time2Work.Time2Work.Mod.Setting.park_avgday]": "Среднее количество часов, которое человек тратит на посещение парков в день.",
"Options.OPTION[Time2Work.Time2Work.Mod.Setting.park_saturday]": "Суббота",
"Options.OPTION_DESCRIPTION[Time2Work.Time2Work.Mod.Setting.park_saturday]": "Среднее количество часов, которое человек тратит на посещение парков в день.",
"Options.OPTION[Time2Work.Time2Work.Mod.Setting.park_sunday]": "Воскресенье",
"Options.OPTION_DESCRIPTION[Time2Work.Time2Work.Mod.Setting.park_sunday]": "Среднее количество часов, которое человек тратит на посещение парков в день.",
"Options.OPTION[Time2Work.Time2Work.Mod.Setting.travel_weekday]": "Понедельник–четверг",
"Options.OPTION_DESCRIPTION[Time2Work.Time2Work.Mod.Setting.travel_weekday]": "Среднее количество часов, которое человек тратит на поездки в день.",
"Options.OPTION[Time2Work.Time2Work.Mod.Setting.travel_avgday]": "Пятница",
"Options.OPTION_DESCRIPTION[Time2Work.Time2Work.Mod.Setting.travel_avgday]": "Среднее количество часов, которое человек тратит на поездки в день.",
"Options.OPTION[Time2Work.Time2Work.Mod.Setting.travel_saturday]": "Суббота",
"Options.OPTION_DESCRIPTION[Time2Work.Time2Work.Mod.Setting.travel_saturday]": "Среднее количество часов, которое человек тратит на поездки в день.",
"Options.OPTION[Time2Work.Time2Work.Mod.Setting.travel_sunday]": "Воскресенье",
"Options.OPTION_DESCRIPTION[Time2Work.Time2Work.Mod.Setting.travel_sunday]": "Среднее количество часов, которое человек тратит на поездки в день.",
"Options.OPTION[Time2Work.Time2Work.Mod.Setting.school_lv1_weekday_pct]": "Понедельник–четверг",
"Options.OPTION_DESCRIPTION[Time2Work.Time2Work.Mod.Setting.school_lv1_weekday_pct]": "Процент учеников, которые посещают школу с понедельника по четверг.",
"Options.OPTION[Time2Work.Time2Work.Mod.Setting.school_lv1_avgday_pct]": "Пятница",
"Options.OPTION_DESCRIPTION[Time2Work.Time2Work.Mod.Setting.school_lv1_avgday_pct]": "Процент учеников, которые посещают школу в пятницу.",
"Options.OPTION[Time2Work.Time2Work.Mod.Setting.school_lv1_saturday_pct]": "Суббота",
"Options.OPTION_DESCRIPTION[Time2Work.Time2Work.Mod.Setting.school_lv1_saturday_pct]": "Процент учеников, которые посещают школу в субботу.",
"Options.OPTION[Time2Work.Time2Work.Mod.Setting.school_lv1_sunday_pct]": "Воскресенье",
"Options.OPTION_DESCRIPTION[Time2Work.Time2Work.Mod.Setting.school_lv1_sunday_pct]": "Процент учеников, которые посещают школу в воскресенье.",
"Options.OPTION[Time2Work.Time2Work.Mod.Setting.school_lv2_weekday_pct]": "Понедельник–четверг",
"Options.OPTION_DESCRIPTION[Time2Work.Time2Work.Mod.Setting.school_lv2_weekday_pct]": "Процент учеников, которые посещают школу с понедельника по четверг.",
"Options.OPTION[Time2Work.Time2Work.Mod.Setting.school_lv2_avgday_pct]": "Пятница",
"Options.OPTION_DESCRIPTION[Time2Work.Time2Work.Mod.Setting.school_lv2_avgday_pct]": "Процент учеников, которые посещают школу в пятницу",
"Options.OPTION[Time2Work.Time2Work.Mod.Setting.school_lv2_saturday_pct]": "Суббота",
"Options.OPTION_DESCRIPTION[Time2Work.Time2Work.Mod.Setting.school_lv2_saturday_pct]": "Процент учеников, которые посещают школу в субботу",
"Options.OPTION[Time2Work.Time2Work.Mod.Setting.school_lv2_sunday_pct]": "Воскресенье",
"Options.OPTION_DESCRIPTION[Time2Work.Time2Work.Mod.Setting.school_lv2_sunday_pct]": "Процент учеников, которые посещают школу в воскресенье",
"Options.OPTION[Time2Work.Time2Work.Mod.Setting.school_lv34_weekday_pct]": "Понедельник–четверг",
"Options.OPTION_DESCRIPTION[Time2Work.Time2Work.Mod.Setting.school_lv34_weekday_pct]": "Процент студентов, которые посещают колледж или университет с понедельника по четверг",
"Options.OPTION[Time2Work.Time2Work.Mod.Setting.school_lv34_avgday_pct]": "Пятница",
"Options.OPTION_DESCRIPTION[Time2Work.Time2Work.Mod.Setting.school_lv34_avgday_pct]": "Процент студентов, которые посещают колледж или университет в пятницу",
"Options.OPTION[Time2Work.Time2Work.Mod.Setting.school_lv34_saturday_pct]": "Суббота",
"Options.OPTION_DESCRIPTION[Time2Work.Time2Work.Mod.Setting.school_lv34_saturday_pct]": "Процент студентов, которые посещают колледж или университет в субботу",
"Options.OPTION[Time2Work.Time2Work.Mod.Setting.school_lv34_sunday_pct]": "Воскресенье",
"Options.OPTION_DESCRIPTION[Time2Work.Time2Work.Mod.Setting.school_lv34_sunday_pct]": "Процент студентов, которые посещают колледж или университет в воскресенье",
"Options.OPTION[Time2Work.Time2Work.Mod.Setting.office_weekday_pct]": "Понедельник–четверг",
"Options.OPTION_DESCRIPTION[Time2Work.Time2Work.Mod.Setting.office_weekday_pct]": "Процент работников, которые работают с понедельника по четверг",
"Options.OPTION[Time2Work.Time2Work.Mod.Setting.office_avgday_pct]": "Пятница",
"Options.OPTION_DESCRIPTION[Time2Work.Time2Work.Mod.Setting.office_avgday_pct]": "Процент работников, которые работают в пятницу",
"Options.OPTION[Time2Work.Time2Work.Mod.Setting.office_sat_pct]": "Суббота",
"Options.OPTION_DESCRIPTION[Time2Work.Time2Work.Mod.Setting.office_sat_pct]": "Процент работников, которые работают в субботу",
"Options.OPTION[Time2Work.Time2Work.Mod.Setting.office_sun_pct]": "Воскресенье",
"Options.OPTION_DESCRIPTION[Time2Work.Time2Work.Mod.Setting.office_sun_pct]": "Процент работников, которые работают в воскресенье",
"Options.OPTION[Time2Work.Time2Work.Mod.Setting.industry_weekday_pct]": "Понедельник–четверг",
"Options.OPTION_DESCRIPTION[Time2Work.Time2Work.Mod.Setting.industry_weekday_pct]": "Процент работников, которые работают с понедельника по четверг",
"Options.OPTION[Time2Work.Time2Work.Mod.Setting.industry_avgday_pct]": "Пятница",
"Options.OPTION_DESCRIPTION[Time2Work.Time2Work.Mod.Setting.industry_avgday_pct]": "Процент работников, которые работают в пятницу",
"Options.OPTION[Time2Work.Time2Work.Mod.Setting.industry_sat_pct]": "Суббота",
"Options.OPTION_DESCRIPTION[Time2Work.Time2Work.Mod.Setting.industry_sat_pct]": "Процент работников, которые работают в субботу",
"Options.OPTION[Time2Work.Time2Work.Mod.Setting.industry_sun_pct]": "Воскресенье",
"Options.OPTION_DESCRIPTION[Time2Work.Time2Work.Mod.Setting.industry_sun_pct]": "Процент работников, которые работают в воскресенье",
"Options.OPTION[Time2Work.Time2Work.Mod.Setting.commercial_weekday_pct]": "Понедельник–четверг",
"Options.OPTION_DESCRIPTION[Time2Work.Time2Work.Mod.Setting.commercial_weekday_pct]": "Процент работников, которые работают с понедельника по четверг",
"Options.OPTION[Time2Work.Time2Work.Mod.Setting.commercial_avgday_pct]": "Пятница",
"Options.OPTION_DESCRIPTION[Time2Work.Time2Work.Mod.Setting.commercial_avgday_pct]": "Процент работников, которые работают в пятницу",
"Options.OPTION[Time2Work.Time2Work.Mod.Setting.commercial_sat_pct]": "Суббота",
"Options.OPTION_DESCRIPTION[Time2Work.Time2Work.Mod.Setting.commercial_sat_pct]": "Процент работников, которые работают в субботу",
"Options.OPTION[Time2Work.Time2Work.Mod.Setting.commercial_sun_pct]": "Воскресенье",
"Options.OPTION_DESCRIPTION[Time2Work.Time2Work.Mod.Setting.commercial_sun_pct]": "Процент работников, которые работают в воскресенье",
"Options.OPTION[Time2Work.Time2Work.Mod.Setting.cityServices_weekday_pct]": "Понедельник–четверг",
"Options.OPTION_DESCRIPTION[Time2Work.Time2Work.Mod.Setting.cityServices_weekday_pct]": "Процент работников, которые работают с понедельника по четверг",
"Options.OPTION[Time2Work.Time2Work.Mod.Setting.cityServices_avgday_pct]": "Пятница",
"Options.OPTION_DESCRIPTION[Time2Work.Time2Work.Mod.Setting.cityServices_avgday_pct]": "Процент работников, которые работают в пятницу",
"Options.OPTION[Time2Work.Time2Work.Mod.Setting.cityServices_sat_pct]": "Суббота",
"Options.OPTION_DESCRIPTION[Time2Work.Time2Work.Mod.Setting.cityServices_sat_pct]": "Процент работников, которые работают в субботу",
"Options.OPTION[Time2Work.Time2Work.Mod.Setting.cityServices_sun_pct]": "Воскресенье",
"Options.OPTION_DESCRIPTION[Time2Work.Time2Work.Mod.Setting.cityServices_sun_pct]": "Процент работников, которые работают в воскресенье",
"Options.OPTION[Time2Work.Time2Work.Mod.Setting.evening_share]": "Вечер",
"Options.OPTION_DESCRIPTION[Time2Work.Time2Work.Mod.Setting.evening_share]": "Процент вечерних рабочих мест",
"Options.OPTION[Time2Work.Time2Work.Mod.Setting.night_share]": "Ночь",
"Options.OPTION_DESCRIPTION[Time2Work.Time2Work.Mod.Setting.night_share]": "Процент ночных рабочих мест",
"Options.OPTION[Time2Work.Time2Work.Mod.Setting.nonday_office_share]": "Офис",
"Options.OPTION_DESCRIPTION[Time2Work.Time2Work.Mod.Setting.nonday_office_share]": "Процент вечерних и ночных рабочих мест",
"Options.OPTION[Time2Work.Time2Work.Mod.Setting.nonday_commercial_share]": "Коммерческие",
"Options.OPTION_DESCRIPTION[Time2Work.Time2Work.Mod.Setting.nonday_commercial_share]": "Процент вечерних и ночных рабочих мест",
"Options.OPTION[Time2Work.Time2Work.Mod.Setting.nonday_industry_share]": "Промышленность",
"Options.OPTION_DESCRIPTION[Time2Work.Time2Work.Mod.Setting.nonday_industry_share]": "Процент вечерних и ночных рабочих мест",
"Options.OPTION[Time2Work.Time2Work.Mod.Setting.nonday_cityservices_share]": "Городские службы",
"Options.OPTION_DESCRIPTION[Time2Work.Time2Work.Mod.Setting.nonday_cityservices_share]": "Процент вечерних и ночных рабочих мест",
"Options.OPTION[Time2Work.Time2Work.Mod.Setting.part_time_percentage]": "Процент неполного рабочего дня",
"Options.OPTION_DESCRIPTION[Time2Work.Time2Work.Mod.Setting.part_time_percentage]": "Процент работников дневной смены, работающих неполный день. Эти работники работают либо утром, либо днем. Они не делают перерыв на обед, а более высокое значение увеличивает поездки в середине дня и снижает пики час-пик.",
"Options.OPTION[Time2Work.Time2Work.Mod.Setting.remote_percentage]": "Процент удаленных работников",
"Options.OPTION_DESCRIPTION[Time2Work.Time2Work.Mod.Setting.remote_percentage]": "Процент работников, работающих из дома. Эти работники могут выходить на обед. Удаленная работа применяется только к офисам и городским службам.",
"Options.OPTION[Time2Work.Time2Work.Mod.Setting.delay_factor]": "Фактор задержки/раннего прихода",
"Options.OPTION_DESCRIPTION[Time2Work.Time2Work.Mod.Setting.delay_factor]": "Этот фактор регулирует вариацию времени прихода и ухода с работы. Более высокое значение увеличивает разброс времени прихода и ухода, т.е. больше жителей не придут вовремя или будут работать дольше. Значение 0 отключает эту функцию. Эффект утром и вечером различается: утром равная вероятность прихода раньше или позже, а вечером вероятность задержки ухода выше, чем раннего ухода. Это реализовано для более реалистичной симуляции поездок.",
"Options.OPTION[Time2Work.Time2Work.Mod.Setting.peak_spread]": "Разгрузка пиков",
"Options.OPTION_DESCRIPTION[Time2Work.Time2Work.Mod.Setting.peak_spread]": "Если включено, жители с длинной дорогой на работу выйдут раньше, чтобы избежать пробок.",
"Options.OPTION[Time2Work.Time2Work.Mod.Setting.lunch_break_percentage]": "Вероятность обеденного перерыва",
"Options.OPTION_DESCRIPTION[Time2Work.Time2Work.Mod.Setting.lunch_break_percentage]": "Вероятность того, что работники сделают перерыв на обед. Во время обеда они могут сходить за продуктами или развлечениями, а затем вернуться на работу.",
"Options.OPTION[Time2Work.Time2Work.Mod.Setting.disable_early_shop_leisure]": "Отключить ранние покупки и развлечения",
"Options.OPTION_DESCRIPTION[Time2Work.Time2Work.Mod.Setting.disable_early_shop_leisure]": "В оригинальной игре жители могут ходить за покупками и отдыхом с 4 утра. Эта опция сдвигает время начала на 8–10 утра.",
"Options.OPTION[Time2Work.Time2Work.Mod.Setting.use_vanilla_timeoff]": "Отключить функцию отпусков и праздников",
"Options.OPTION_DESCRIPTION[Time2Work.Time2Work.Mod.Setting.use_vanilla_timeoff]": "Отключает модифицированную систему отпусков и использует оригинальную. В оригинальной игре вероятность отдыха жителей составляет 60% каждый день.",
"Options.OPTION[Time2Work.Time2Work.Mod.Setting.use_school_vanilla_timeoff]": "Отключить отпуск и праздники для школ",
"Options.OPTION_DESCRIPTION[Time2Work.Time2Work.Mod.Setting.use_school_vanilla_timeoff]": "Отключает модифицированную систему отпусков для школ и использует оригинальную. В оригинальной игре вероятность не посещать школу составляет 60%.",
"Options.OPTION[Time2Work.Time2Work.Mod.Setting.holidays_per_year]": "Количество праздников в году",
"Options.OPTION_DESCRIPTION[Time2Work.Time2Work.Mod.Setting.holidays_per_year]": "Для большинства стран значение должно быть от 10 до 15. Значение по умолчанию подходит для большинства стран.",
"Options.OPTION[Time2Work.Time2Work.Mod.Setting.vacation_per_year]": "Количество дней отпуска в году",
"Options.OPTION_DESCRIPTION[Time2Work.Time2Work.Mod.Setting.vacation_per_year]": "Количество дней отпуска в году, без учета выходных. Для стран с месяцем отпуска используйте 22. Для США более реалистично значение 11.",
"Options.OPTION[Time2Work.Time2Work.Mod.Setting.school_vacation_month1]": "Месяц отпуска 1:",
"Options.OPTION_DESCRIPTION[Time2Work.Time2Work.Mod.Setting.school_vacation_month1]": "Месяц, когда школы будут закрыты на отпуск.",
"Options.OPTION[Time2Work.Time2Work.Mod.Setting.school_vacation_month2]": "Месяц отпуска 2:",
"Options.OPTION_DESCRIPTION[Time2Work.Time2Work.Mod.Setting.school_vacation_month2]": "Месяц, когда школы будут закрыты на отпуск.",
"Options.OPTION[Time2Work.Time2Work.Mod.Setting.dt_simulation]": "Выбор поведения симуляции типа дня",
"Options.OPTION_DESCRIPTION[Time2Work.Time2Work.Mod.Setting.dt_simulation]": "Эта опция изменяет поведение симуляции в течение дня. «Средний день» соответствует поведению Vanilla, сочетая будние и выходные дни. С настройками отпуска/праздников по умолчанию (вкладка «Покупки и отдых») в «Средний день» около 30% жителей будут вести себя как в выходной день — больше отдыхать и делать покупки, а остальные будут работать или учиться. Опция «Будний день» увеличивает работу и учебу, снижая отдых и покупки. «Выходные» делают наоборот. В выходные школы закрыты. «7-дневная неделя» будет чередовать будние и выходные с понедельника по воскресенье.",
"Options.OPTION[Time2Work.Time2Work.Mod.Setting.school_start_time]": "Время начала начальной школы",
"Options.OPTION_DESCRIPTION[Time2Work.Time2Work.Mod.Setting.school_start_time]": "Время начала занятий в начальных школах.",
"Options.OPTION[Time2Work.Time2Work.Mod.Setting.school_end_time]": "Время окончания начальной школы",
"Options.OPTION_DESCRIPTION[Time2Work.Time2Work.Mod.Setting.school_end_time]": "Время окончания занятий в начальных школах.",
"Options.OPTION[Time2Work.Time2Work.Mod.Setting.high_school_start_time]": "Время начала средней школы",
"Options.OPTION_DESCRIPTION[Time2Work.Time2Work.Mod.Setting.high_school_start_time]": "Время начала занятий в средних школах.",
"Options.OPTION[Time2Work.Time2Work.Mod.Setting.high_school_end_time]": "Время окончания средней школы",
"Options.OPTION_DESCRIPTION[Time2Work.Time2Work.Mod.Setting.high_school_end_time]": "Время окончания занятий в средних школах.",
"Options.OPTION[Time2Work.Time2Work.Mod.Setting.univ_start_time]": "Время начала колледжа/университета",
"Options.OPTION_DESCRIPTION[Time2Work.Time2Work.Mod.Setting.univ_start_time]": "Время начала занятий в колледжах и университетах.",
"Options.OPTION[Time2Work.Time2Work.Mod.Setting.univ_end_time]": "Время окончания колледжа/университета",
"Options.OPTION_DESCRIPTION[Time2Work.Time2Work.Mod.Setting.univ_end_time]": "Время окончания занятий в колледжах и университетах.",
"Options.OPTION[Time2Work.Time2Work.Mod.Setting.work_start_time]": "Время начала рабочей смены",
"Options.OPTION_DESCRIPTION[Time2Work.Time2Work.Mod.Setting.work_start_time]": "Время начала дневной рабочей смены.",
"Options.OPTION[Time2Work.Time2Work.Mod.Setting.work_end_time]": "Время окончания рабочей смены",
"Options.OPTION_DESCRIPTION[Time2Work.Time2Work.Mod.Setting.work_end_time]": "Время окончания дневной рабочей смены.",
"Options.OPTION[Time2Work.Time2Work.Mod.Setting.avg_work_hours_ft_wd]": "Средние часы работы для работников полного дня",
"Options.OPTION_DESCRIPTION[Time2Work.Time2Work.Mod.Setting.avg_work_hours_ft_wd]": "Среднее количество часов, отработанных работниками полного дня в будний день",
"Options.OPTION[Time2Work.Time2Work.Mod.Setting.avg_work_hours_pt_wd]": "Средние часы работы для работников неполного дня",
"Options.OPTION_DESCRIPTION[Time2Work.Time2Work.Mod.Setting.avg_work_hours_pt_wd]": "Среднее количество часов, отработанных работниками неполного дня в будний день",
"Options.OPTION[Time2Work.Time2Work.Mod.Setting.slow_time_factor]": "Фактор замедления времени",
"Options.OPTION_DESCRIPTION[Time2Work.Time2Work.Mod.Setting.slow_time_factor]": "Этот фактор замедляет течение времени и увеличивает продолжительность дня. Значение 1 — без эффекта, значение 2 — день длится в два раза дольше. Скорость симуляции при этом не изменяется, а другие системы обновляются в зависимости от скорости симуляции, а не длины дня.",
"Options.OPTION[Time2Work.Time2Work.Mod.Setting.daysPerMonth]": "Дней в месяце",
"Options.OPTION_DESCRIPTION[Time2Work.Time2Work.Mod.Setting.daysPerMonth]": "Изменяет количество дней в месяце. Значение по умолчанию — 1.",
"Options.OPTION[Time2Work.Time2Work.Mod.Setting.tourism_trips]": "Вариация туризма по дням недели",
"Options.OPTION_DESCRIPTION[Time2Work.Time2Work.Mod.Setting.tourism_trips]": "Увеличивает число туристов в выходные и уменьшает в будние дни.",
"Options.OPTION[Time2Work.Time2Work.Mod.Setting.commuter_trips]": "Вариация поездок на работу по дням недели",
"Options.OPTION_DESCRIPTION[Time2Work.Time2Work.Mod.Setting.commuter_trips]": "Увеличивает количество поездок на работу в будние дни и снижает в выходные. Также увеличивает вероятность прибытия на работу самолетом.",
"Options.OPTION[Time2Work.Time2Work.Mod.Setting.service_expenses_night_reduction]": "Снижение стоимости услуг ночью",
"Options.OPTION_DESCRIPTION[Time2Work.Time2Work.Mod.Setting.service_expenses_night_reduction]": "Снижает стоимость услуг с 23:00 до 6:00.",
"Options.OPTION[Time2Work.Time2Work.Mod.Setting.trafficReduction]": "Снижение трафика",
"Options.OPTION_DESCRIPTION[Time2Work.Time2Work.Mod.Setting.trafficReduction]": "Меньшие значения увеличивают трафик в городе. Значение Vanilla — 5. Ноль — максимум трафика.",
"Options.OPTION[Time2Work.Time2Work.Mod.Setting.min_attraction]": "Мин. привлекательность",
"Options.OPTION_DESCRIPTION[Time2Work.Time2Work.Mod.Setting.min_attraction]": "Увеличение или уменьшение этого значения изменяет количество парков, способных проводить специальные события.",
"Options.OPTION[Time2Work.Time2Work.Mod.Setting.min_event_weekday]": "Понедельник–четверг",
"Options.OPTION_DESCRIPTION[Time2Work.Time2Work.Mod.Setting.min_event_weekday]": "Минимальное количество событий с понедельника по четверг",
"Options.OPTION[Time2Work.Time2Work.Mod.Setting.min_event_avg_day]": "Пятница",
"Options.OPTION_DESCRIPTION[Time2Work.Time2Work.Mod.Setting.min_event_avg_day]": "Минимальное количество событий в пятницу",
"Options.OPTION[Time2Work.Time2Work.Mod.Setting.min_event_weekend]": "Выходные",
"Options.OPTION_DESCRIPTION[Time2Work.Time2Work.Mod.Setting.min_event_weekend]": "Минимальное количество событий в выходные",
"Options.OPTION[Time2Work.Time2Work.Mod.Setting.max_event_weekday]": "Понедельник–четверг",
"Options.OPTION_DESCRIPTION[Time2Work.Time2Work.Mod.Setting.max_event_weekday]": "Максимальное количество событий с понедельника по четверг",
"Options.OPTION[Time2Work.Time2Work.Mod.Setting.max_event_avg_day]": "Пятница",
"Options.OPTION_DESCRIPTION[Time2Work.Time2Work.Mod.Setting.max_event_avg_day]": "Максимальное количество событий в пятницу",
"Options.OPTION[Time2Work.Time2Work.Mod.Setting.max_event_weekend]": "Выходные",
"Options.OPTION_DESCRIPTION[Time2Work.Time2Work.Mod.Setting.max_event_weekend]": "Максимальное количество событий в выходные",
"Options.OPTION[Time2Work.Time2Work.Mod.Setting.avg_time_beverages]": "Напитки",
"Options.OPTION_DESCRIPTION[Time2Work.Time2Work.Mod.Setting.avg_time_beverages]": "Среднее время в минутах на покупку напитков.",
"Options.OPTION[Time2Work.Time2Work.Mod.Setting.avg_time_chemicals]": "Химические товары",
"Options.OPTION_DESCRIPTION[Time2Work.Time2Work.Mod.Setting.avg_time_chemicals]": "Среднее время в минутах на покупку химических товаров.",
"Options.OPTION[Time2Work.Time2Work.Mod.Setting.avg_time_convenienceFood]": "Готовая еда",
"Options.OPTION_DESCRIPTION[Time2Work.Time2Work.Mod.Setting.avg_time_convenienceFood]": "Среднее время в минутах на покупку готовой еды.",
"Options.OPTION[Time2Work.Time2Work.Mod.Setting.avg_time_electronics]": "Электроника",
"Options.OPTION_DESCRIPTION[Time2Work.Time2Work.Mod.Setting.avg_time_electronics]": "Среднее время в минутах на покупку электроники.",
"Options.OPTION[Time2Work.Time2Work.Mod.Setting.avg_time_software]": "Программное обеспечение",
"Options.OPTION_DESCRIPTION[Time2Work.Time2Work.Mod.Setting.avg_time_software]": "Среднее время в минутах на покупку программного обеспечения.",
"Options.OPTION[Time2Work.Time2Work.Mod.Setting.avg_time_financial]": "Финансовые услуги",
"Options.OPTION_DESCRIPTION[Time2Work.Time2Work.Mod.Setting.avg_time_financial]": "Среднее время в минутах на получение финансовых услуг.",
"Options.OPTION[Time2Work.Time2Work.Mod.Setting.avg_time_food]": "Продукты",
"Options.OPTION_DESCRIPTION[Time2Work.Time2Work.Mod.Setting.avg_time_food]": "Среднее время в минутах на покупку продуктов.",
"Options.OPTION[Time2Work.Time2Work.Mod.Setting.avg_time_furniture]": "Мебель",
"Options.OPTION_DESCRIPTION[Time2Work.Time2Work.Mod.Setting.avg_time_furniture]": "Среднее время в минутах на покупку мебели.",
"Options.OPTION[Time2Work.Time2Work.Mod.Setting.avg_time_meals]": "Блюда",
"Options.OPTION_DESCRIPTION[Time2Work.Time2Work.Mod.Setting.avg_time_meals]": "Среднее время в минутах на покупку блюд.",
"Options.OPTION[Time2Work.Time2Work.Mod.Setting.avg_time_media]": "Медиа",
"Options.OPTION_DESCRIPTION[Time2Work.Time2Work.Mod.Setting.avg_time_media]": "Среднее время в минутах на покупку медиа.",
"Options.OPTION[Time2Work.Time2Work.Mod.Setting.avg_time_paper]": "Бумага",
"Options.OPTION_DESCRIPTION[Time2Work.Time2Work.Mod.Setting.avg_time_paper]": "Среднее время в минутах на покупку бумажной продукции.",
"Options.OPTION[Time2Work.Time2Work.Mod.Setting.avg_time_petrochemicals]": "Нефтехимия",
"Options.OPTION_DESCRIPTION[Time2Work.Time2Work.Mod.Setting.avg_time_petrochemicals]": "Среднее время в минутах на покупку нефтехимической продукции.",
"Options.OPTION[Time2Work.Time2Work.Mod.Setting.avg_time_pharmaceuticals]": "Фармацевтика",
"Options.OPTION_DESCRIPTION[Time2Work.Time2Work.Mod.Setting.avg_time_pharmaceuticals]": "Среднее время в минутах на покупку фармацевтической продукции.",
"Options.OPTION[Time2Work.Time2Work.Mod.Setting.avg_time_plastics]": "Пластмассы",
"Options.OPTION_DESCRIPTION[Time2Work.Time2Work.Mod.Setting.avg_time_plastics]": "Среднее время в минутах на покупку пластмасс.",
"Options.OPTION[Time2Work.Time2Work.Mod.Setting.avg_time_telecom]": "Телеком",
"Options.OPTION_DESCRIPTION[Time2Work.Time2Work.Mod.Setting.avg_time_telecom]": "Среднее время в минутах на покупку телеком-услуг.",
"Options.OPTION[Time2Work.Time2Work.Mod.Setting.avg_time_textiles]": "Текстиль",
"Options.OPTION_DESCRIPTION[Time2Work.Time2Work.Mod.Setting.avg_time_textiles]": "Среднее время в минутах на покупку текстиля.",
"Options.OPTION[Time2Work.Time2Work.Mod.Setting.avg_time_recreation]": "Отдых",
"Options.OPTION_DESCRIPTION[Time2Work.Time2Work.Mod.Setting.avg_time_recreation]": "Среднее время в минутах на покупку товаров для отдыха.",
"Options.OPTION[Time2Work.Time2Work.Mod.Setting.avg_time_entertainment]": "Развлечения",
"Options.OPTION_DESCRIPTION[Time2Work.Time2Work.Mod.Setting.avg_time_entertainment]": "Среднее время в минутах на покупку товаров для развлечений.",
"Options.OPTION[Time2Work.Time2Work.Mod.Setting.avg_time_vehicles]": "Транспортные средства",
"Options.OPTION_DESCRIPTION[Time2Work.Time2Work.Mod.Setting.avg_time_vehicles]": "Среднее время в минутах на покупку транспортных средств.",
"Options.Time2Work.Time2Work.Mod.DTSIMULATIONENUM[AverageDay]": "Обычный день",
"Options.Time2Work.Time2Work.Mod.DTSIMULATIONENUM[Weekday]": "Будний день",
"Options.Time2Work.Time2Work.Mod.DTSIMULATIONENUM[Saturday]": "Суббота",
"Options.Time2Work.Time2Work.Mod.DTSIMULATIONENUM[Sunday]": "Воскресенье",
"Options.Time2Work.Time2Work.Mod.DTSIMULATIONENUM[sevendayweek]": "7-дневная неделя (Понедельник–Воскресенье)",
"Options.Time2Work.Time2Work.Mod.SETTINGSENUM[Performance]": "Производительность",
"Options.Time2Work.Time2Work.Mod.SETTINGSENUM[Balanced]": "Сбалансированный",
"Options.Time2Work.Time2Work.Mod.SETTINGSENUM[USA]": "Соединённые Штаты Америки",
"Options.Time2Work.Time2Work.Mod.SETTINGSENUM[Singapore]": "Сингапур",
"Options.Time2Work.Time2Work.Mod.SETTINGSENUM[UK]": "Великобритания",
"Options.Time2Work.Time2Work.Mod.SETTINGSENUM[Brazil]": "Бразилия",
"Options.Time2Work.Time2Work.Mod.SETTINGSENUM[Canada]": "Канада",
"Options.Time2Work.Time2Work.Mod.SETTINGSENUM[Phillipines]": "Филиппины",
"Options.Time2Work.Time2Work.Mod.SETTINGSENUM[Netherlands]": "Нидерланды",
"Options.Time2Work.Time2Work.Mod.SETTINGSENUM[France]": "Франция",
"Options.Time2Work.Time2Work.Mod.SETTINGSENUM[Germany]": "Германия",
"Options.Time2Work.Time2Work.Mod.SETTINGSENUM[Poland]": "Польша",
"Options.Time2Work.Time2Work.Mod.TIMEENUM[t700]": "07:00",
"Options.Time2Work.Time2Work.Mod.TIMEENUM[t730]": "07:30",
"Options.Time2Work.Time2Work.Mod.TIMEENUM[t800]": "08:00",
"Options.Time2Work.Time2Work.Mod.TIMEENUM[t830]": "08:30",
"Options.Time2Work.Time2Work.Mod.TIMEENUM[t900]": "09:00",
"Options.Time2Work.Time2Work.Mod.TIMEENUM[t930]": "09:30",
"Options.Time2Work.Time2Work.Mod.TIMEENUM[t1000]": "10:00",
"Options.Time2Work.Time2Work.Mod.TIMEENUM[t1030]": "10:30",
"Options.Time2Work.Time2Work.Mod.TIMEENUM[t1100]": "11:00",
"Options.Time2Work.Time2Work.Mod.TIMEENUM[t1130]": "11:30",
"Options.Time2Work.Time2Work.Mod.TIMEENUM[t1200]": "12:00",
"Options.Time2Work.Time2Work.Mod.TIMEENUM[t1230]": "12:30",
"Options.Time2Work.Time2Work.Mod.TIMEENUM[t1300]": "13:00",
"Options.Time2Work.Time2Work.Mod.TIMEENUM[t1330]": "13:30",
"Options.Time2Work.Time2Work.Mod.TIMEENUM[t1400]": "14:00",
"Options.Time2Work.Time2Work.Mod.TIMEENUM[t1430]": "14:30",
"Options.Time2Work.Time2Work.Mod.TIMEENUM[t1500]": "15:00",
"Options.Time2Work.Time2Work.Mod.TIMEENUM[t1530]": "15:30",
"Options.Time2Work.Time2Work.Mod.TIMEENUM[t1600]": "16:00",
"Options.Time2Work.Time2Work.Mod.TIMEENUM[t1630]": "16:30",
"Options.Time2Work.Time2Work.Mod.TIMEENUM[t1700]": "17:00",
"Options.Time2Work.Time2Work.Mod.TIMEENUM[t1730]": "17:30",
"Options.Time2Work.Time2Work.Mod.TIMEENUM[t1800]": "18:00",
"Options.Time2Work.Time2Work.Mod.TIMEENUM[t1830]": "18:30",
"Options.Time2Work.Time2Work.Mod.TIMEENUM[t1900]": "19:00",
"Options.Time2Work.Time2Work.Mod.TIMEENUM[t1930]": "19:30",
"Options.Time2Work.Time2Work.Mod.TIMEENUM[t2000]": "20:00",
"Options.Time2Work.Time2Work.Mod.MONTHS[January]": "1",
"Options.Time2Work.Time2Work.Mod.MONTHS[February]": "2",
"Options.Time2Work.Time2Work.Mod.MONTHS[March]": "3",
"Options.Time2Work.Time2Work.Mod.MONTHS[April]": "4",
"Options.Time2Work.Time2Work.Mod.MONTHS[May]": "5",
"Options.Time2Work.Time2Work.Mod.MONTHS[June]": "6",
"Options.Time2Work.Time2Work.Mod.MONTHS[July]": "7",
"Options.Time2Work.Time2Work.Mod.MONTHS[August]": "8",
"Options.Time2Work.Time2Work.Mod.MONTHS[September]": "9",
"Options.Time2Work.Time2Work.Mod.MONTHS[October]": "10",
"Options.Time2Work.Time2Work.Mod.MONTHS[November]": "11",
"Options.Time2Work.Time2Work.Mod.MONTHS[December]": "12",
"Options.Time2Work.Time2Work.Mod.DAYOFWEEK[Sunday]": "Вс",
"Options.Time2Work.Time2Work.Mod.DAYOFWEEK[Monday]": "Пн",
"Options.Time2Work.Time2Work.Mod.DAYOFWEEK[Tuesday]": "Вт",
"Options.Time2Work.Time2Work.Mod.DAYOFWEEK[Wednesday]": "Ср",
"Options.Time2Work.Time2Work.Mod.DAYOFWEEK[Thursday]": "Чт",
"Options.Time2Work.Time2Work.Mod.DAYOFWEEK[Friday]": "Пт",
"Options.Time2Work.Time2Work.Mod.DAYOFWEEK[Saturday]": "Сб",
"t2w.chirp.special_event.today": "Сегодня особое событие с {start} до {end} в",
"t2w.chirp.special_event.starting": "Скоро начнётся особое событие в",
"t2w.chirp.special_event.ending": "Особое событие скоро закончится в",
"t2w.chirp.holiday.new_year": "С Новым Годом!",
"t2w.chirp.mod_name": "Мод Реалистичные Походы"
}