{
  "Options.OPTION[TimeWeatherAnarchy.TimeWeatherAnarchy.Mod.TimeWeatherAnarchySettings.TriggerPanelToggle]": "Enable Tool Hotkey",
  "Options.OPTION[TimeWeatherAnarchy.TimeWeatherAnarchy.Mod/TriggerPanelToggle/binding]": "Enable Tool Hotkey",
  "Options.OPTION_DESCRIPTION[TimeWeatherAnarchy.TimeWeatherAnarchy.Mod.TimeWeatherAnarchySettings.TriggerPanelToggle]": "Open or close the tool.",
  "Options.OPTION[TimeWeatherAnarchy.TimeWeatherAnarchy.Mod.TimeWeatherAnarchySettings.TriggerDayNightToggle]": "Switch Day or Night Time Hotkey",
  "Options.OPTION[TimeWeatherAnarchy.TimeWeatherAnarchy.Mod/TriggerDayNightToggle/binding]": "Switch Day or Night Time Hotkey",
  "Options.OPTION_DESCRIPTION[TimeWeatherAnarchy.TimeWeatherAnarchy.Mod.TimeWeatherAnarchySettings.TriggerDayNightToggle]": "Switch between day or night time when pressing this toggle.",
  "Options.OPTION[TimeWeatherAnarchy.TimeWeatherAnarchy.Mod/TriggerNextProfileToggle/binding]": "Go to the next settings profile Hotkey",
  "Options.OPTION_DESCRIPTION[TimeWeatherAnarchy.TimeWeatherAnarchy.Mod.TimeWeatherAnarchySettings.TriggerNextProfileToggle]": "Change your settings profile to the next one.",
  "Options.SECTION[TimeWeatherAnarchy.TimeWeatherAnarchy.Mod]": "Time & Weather Anarchy",
  "Options.TAB[TimeWeatherAnarchy.TimeWeatherAnarchy.Mod.Main]": "General Settings",
  "Options.GROUP[TimeWeatherAnarchy.TimeWeatherAnarchy.Mod.Main]": "General Settings",
  "Options.GROUP[TimeWeatherAnarchy.TimeWeatherAnarchy.Mod.KeyBindingGroup]": "Key Binding",
  
  "TimeWeatherAnarchy.ModName": "Time & Weather Anarchy",
  "TimeWeatherAnarchy.ModIconTooltip": "Time & Weather Anarchy",
  "TimeWeatherAnarchy.Default": "Default",
  "TimeWeatherAnarchy.Custom": "Custom",
  "TimeWeatherAnarchy.Main": "Main",
  "TimeWeatherAnarchy.TimeOptions": "Time Options",
  "TimeWeatherAnarchy.ProfileOptions": "Profiles",
  "TimeWeatherAnarchy.Create": "Create",
  "TimeWeatherAnarchy.NewProfile": "New Profile",
  "TimeWeatherAnarchy.Latitude": "Sun Latitude",
  "TimeWeatherAnarchy.Longitude": "Sun Longitude",
  "TimeWeatherAnarchy.Delete": "Delete",
  "TimeWeatherAnarchy.CreateProfile": "Create Profile",
  "TimeWeatherAnarchy.UpdateProfile": "Update Profile",
  "TimeWeatherAnarchy.EditProfile": "Edit Profile",
  "TimeWeatherAnarchy.EditingProfile": "Editing Profile",
  "TimeWeatherAnarchy.TypeProfileName": "Profile Name...",
  "TimeWeatherAnarchy.TypeUpdatedProfileName": "Updated Profile Name...",
  "TimeWeatherAnarchy.Cancel": "Cancel",
  "TimeWeatherAnarchy.Edit": "Edit",
  "TimeWeatherAnarchy.Save": "Save",
  "TimeWeatherAnarchy.CopyCurrentProfile": "Copy preferences from current profile",
  "TimeWeatherAnarchy.ProfileOptionsDescription": "Create profiles that save all your preferences and select them",
  "TimeWeatherAnarchy.Day": "Day",
  "TimeWeatherAnarchy.Night": "Night",
  "TimeWeatherAnarchy.HourOfTheDay": "Hour of the day",
  "TimeWeatherAnarchy.DayOfTheYear": "Day of the year",
  "TimeWeatherAnarchy.WeatherOptions": "Weather Options",
  "TimeWeatherAnarchy.RainbowStrength": "Rainbow Strength",
  "TimeWeatherAnarchy.Spring": "Spring",
  "TimeWeatherAnarchy.Summer": "Summer",
  "TimeWeatherAnarchy.Fall": "Fall",
  "TimeWeatherAnarchy.Winter": "Winter",
  "TimeWeatherAnarchy.EnableCustomPrecipitation": "Enable Custom Precipitation",
  "TimeWeatherAnarchy.EnableCustomClouds": "Enable Custom Clouds",
  "TimeWeatherAnarchy.EnableCustomAurora": "Enable Custom Aurora",
  "TimeWeatherAnarchy.EnableCustomTemperature": "Enable Custom Temperature",
  "TimeWeatherAnarchy.EnableCustomFog": "Enable Custom Fog",
  "TimeWeatherAnarchy.EnableCustomThunder": "Enable Custom Thunder",
  "TimeWeatherAnarchy.WeatherDate": "Weather Date",
  "TimeWeatherAnarchy.Precipitation": "Precipitation",
  "TimeWeatherAnarchy.Clouds": "Clouds",
  "TimeWeatherAnarchy.Aurora": "Aurora",
  "TimeWeatherAnarchy.Temperature": "Temperature",
  "TimeWeatherAnarchy.Fog": "Fog",
  "TimeWeatherAnarchy.Thunder": "Thunder",
  "TimeWeatherAnarchy.Rainbow": "Rainbow"
}
